iiblib/__init__.py
iiblib/iib_authentication.py
iiblib/iib_build_details_model.py
iiblib/iib_build_details_pager.py
iiblib/iib_client.py
iiblib/iib_session.py
iiblib-7.4.0.dist-info/LICENSE
iiblib-7.4.0.dist-info/METADATA
iiblib-7.4.0.dist-info/WHEEL
iiblib-7.4.0.dist-info/top_level.txt
iiblib-7.4.0.dist-info/RECORD
