Metadata-Version: 2.1
Name: iiblib
Version: 7.4.0
Summary: IIB client library
Home-page: https://github.com/release-engineering/iiblib
Author: Jindrich Luza
Author-email: jluza@redhat.com
Classifier: Development Status :: 5 - Production/Stable
Classifier: Intended Audience :: Developers
Classifier: License :: OSI Approved :: GNU General Public License v3 or later (GPLv3+)
Classifier: Programming Language :: Python
Classifier: Programming Language :: Python :: 3
Classifier: Programming Language :: Python :: 3.7
Classifier: Programming Language :: Python :: Implementation :: CPython
Classifier: Programming Language :: Python :: Implementation :: PyPy
Requires-Python: >=3.6
License-File: LICENSE
Requires-Dist: requests
Requires-Dist: requests-kerberos
Requires-Dist: kerberos
Requires-Dist: tenacity
Provides-Extra: rest
Requires-Dist: Sphinx; extra == "rest"
